{
  "translation": "Синодальный перевод (1876)",
  "abbreviation": "rst",
  "lang": "ru",
  "language": "Russian",
  "direction": "LTR",
  "encoding": "UTF-8",
  "book_nr": 43,
  "book_name": "Евангелие от Иоанна",
  "chapter": 15,
  "name": "Евангелие от Иоанна 15",
  "verses": [
    {
      "chapter": 15,
      "verse": 1,
      "name": "Евангелие от Иоанна 15:1",
      "text": "Я есмь истинная виноградная лоза, а Отец Мой — виноградарь."
    },
    {
      "chapter": 15,
      "verse": 2,
      "name": "Евангелие от Иоанна 15:2",
      "text": "Всякую у Меня ветвь, не приносящую плода, Он отсекает; и всякую, приносящую плод, очищает, чтобы более принесла плода."
    },
    {
      "chapter": 15,
      "verse": 3,
      "name": "Евангелие от Иоанна 15:3",
      "text": "Вы уже очищены через слово, которое Я проповедал вам."
    },
    {
      "chapter": 15,
      "verse": 4,
      "name": "Евангелие от Иоанна 15:4",
      "text": "Пребудьте во Мне, и Я в вас. Как ветвь не может приносить плода сама собою, если не будет на лозе: так и вы, если не будете во Мне."
    },
    {
      "chapter": 15,
      "verse": 5,
      "name": "Евангелие от Иоанна 15:5",
      "text": "Я есмь лоза, а вы ветви; кто пребывает во Мне, и Я в нем, тот приносит много плода; ибо без Меня не можете делать ничего."
    },
    {
      "chapter": 15,
      "verse": 6,
      "name": "Евангелие от Иоанна 15:6",
      "text": "Кто не пребудет во Мне, извергнется вон, как ветвь, и засохнет; а такие ветви собирают и бросают в огонь, и они сгорают."
    },
    {
      "chapter": 15,
      "verse": 7,
      "name": "Евангелие от Иоанна 15:7",
      "text": "Если пребудете во Мне и слова Мои в вас пребудут, то, чего ни пожелаете, просите, и будет вам."
    },
    {
      "chapter": 15,
      "verse": 8,
      "name": "Евангелие от Иоанна 15:8",
      "text": "Тем прославится Отец Мой, если вы принесете много плода и будете Моими учениками."
    },
    {
      "chapter": 15,
      "verse": 9,
      "name": "Евангелие от Иоанна 15:9",
      "text": "Как возлюбил Меня Отец, и Я возлюбил вас; пребудьте в любви Моей."
    },
    {
      "chapter": 15,
      "verse": 10,
      "name": "Евангелие от Иоанна 15:10",
      "text": "Если заповеди Мои соблюдете, пребудете в любви Моей, как и Я соблюл заповеди Отца Моего и пребываю в Его любви."
    },
    {
      "chapter": 15,
      "verse": 11,
      "name": "Евангелие от Иоанна 15:11",
      "text": "Сие сказал Я вам, да радость Моя в вас пребудет и радость ваша будет совершенна."
    },
    {
      "chapter": 15,
      "verse": 12,
      "name": "Евангелие от Иоанна 15:12",
      "text": "Сия есть заповедь Моя, да любите друг друга, как Я возлюбил вас."
    },
    {
      "chapter": 15,
      "verse": 13,
      "name": "Евангелие от Иоанна 15:13",
      "text": "Нет больше той любви, как если кто положит душу свою за друзей своих."
    },
    {
      "chapter": 15,
      "verse": 14,
      "name": "Евангелие от Иоанна 15:14",
      "text": "Вы друзья Мои, если исполняете то, что Я заповедую вам."
    },
    {
      "chapter": 15,
      "verse": 15,
      "name": "Евангелие от Иоанна 15:15",
      "text": "Я уже не называю вас рабами, ибо раб не знает, что делает господин его; но Я назвал вас друзьями, потому что сказал вам все, что слышал от Отца Моего."
    },
    {
      "chapter": 15,
      "verse": 16,
      "name": "Евангелие от Иоанна 15:16",
      "text": "Не вы Меня избрали, а Я вас избрал и поставил вас, чтобы вы шли и приносили плод, и чтобы плод ваш пребывал, дабы, чего ни попросите от Отца во имя Мое, Он дал вам."
    },
    {
      "chapter": 15,
      "verse": 17,
      "name": "Евангелие от Иоанна 15:17",
      "text": "Сие заповедаю вам, да любите друг друга."
    },
    {
      "chapter": 15,
      "verse": 18,
      "name": "Евангелие от Иоанна 15:18",
      "text": "Если мир вас ненавидит, знайте, что Меня прежде вас возненавидел."
    },
    {
      "chapter": 15,
      "verse": 19,
      "name": "Евангелие от Иоанна 15:19",
      "text": "Если бы вы были от мира, то мир любил бы свое; а как вы не от мира, но Я избрал вас от мира, потому ненавидит вас мир."
    },
    {
      "chapter": 15,
      "verse": 20,
      "name": "Евангелие от Иоанна 15:20",
      "text": "Помните слово, которое Я сказал вам: раб не больше господина своего. Если Меня гнали, будут гнать и вас; если Мое слово соблюдали, будут соблюдать и ваше."
    },
    {
      "chapter": 15,
      "verse": 21,
      "name": "Евангелие от Иоанна 15:21",
      "text": "Но все то сделают вам за имя Мое, потому что не знают Пославшего Меня."
    },
    {
      "chapter": 15,
      "verse": 22,
      "name": "Евангелие от Иоанна 15:22",
      "text": "Если бы Я не пришел и не говорил им, то не имели бы греха; а теперь не имеют извинения во грехе своем."
    },
    {
      "chapter": 15,
      "verse": 23,
      "name": "Евангелие от Иоанна 15:23",
      "text": "Ненавидящий Меня ненавидит и Отца Моего."
    },
    {
      "chapter": 15,
      "verse": 24,
      "name": "Евангелие от Иоанна 15:24",
      "text": "Если бы Я не сотворил между ними дел, каких никто другой не делал, то не имели бы греха; а теперь и видели, и возненавидели и Меня и Отца Моего."
    },
    {
      "chapter": 15,
      "verse": 25,
      "name": "Евангелие от Иоанна 15:25",
      "text": "Но да сбудется слово, написанное в законе их: возненавидели Меня напрасно."
    },
    {
      "chapter": 15,
      "verse": 26,
      "name": "Евангелие от Иоанна 15:26",
      "text": "Когда же приидет Утешитель, Которого Я пошлю вам от Отца, Дух истины, Который от Отца исходит, Он будет свидетельствовать о Мне;"
    },
    {
      "chapter": 15,
      "verse": 27,
      "name": "Евангелие от Иоанна 15:27",
      "text": "а также и вы будете свидетельствовать, потому что вы сначала со Мною. "
    }
  ]
}
