{
  "translation": "Синодальный перевод (1876)",
  "abbreviation": "rst",
  "lang": "ru",
  "language": "Russian",
  "direction": "LTR",
  "encoding": "UTF-8",
  "book_nr": 19,
  "book_name": "Псалтирь",
  "chapter": 139,
  "name": "Псалтирь 139",
  "verses": [
    {
      "chapter": 139,
      "verse": 1,
      "name": "Псалтирь 139:1",
      "text": "Начальнику хора. Псалом Давида."
    },
    {
      "chapter": 139,
      "verse": 2,
      "name": "Псалтирь 139:2",
      "text": "Избавь меня, Господи, от человека злого; сохрани меня от притеснителя:"
    },
    {
      "chapter": 139,
      "verse": 3,
      "name": "Псалтирь 139:3",
      "text": "они злое мыслят в сердце, всякий день ополчаются на брань,"
    },
    {
      "chapter": 139,
      "verse": 4,
      "name": "Псалтирь 139:4",
      "text": "изощряют язык свой, как змея; яд аспида под устами их."
    },
    {
      "chapter": 139,
      "verse": 5,
      "name": "Псалтирь 139:5",
      "text": "Соблюди меня, Господи, от рук нечестивого, сохрани меня от притеснителей, которые замыслили поколебать стопы мои."
    },
    {
      "chapter": 139,
      "verse": 6,
      "name": "Псалтирь 139:6",
      "text": "Гордые скрыли силки для меня и петли, раскинули сеть по дороге, тенета разложили для меня."
    },
    {
      "chapter": 139,
      "verse": 7,
      "name": "Псалтирь 139:7",
      "text": "Я сказал Господу: Ты Бог мой; услышь, Господи, голос молений моих!"
    },
    {
      "chapter": 139,
      "verse": 8,
      "name": "Псалтирь 139:8",
      "text": "Господи, Господи, сила спасения моего! Ты покрыл голову мою в день брани."
    },
    {
      "chapter": 139,
      "verse": 9,
      "name": "Псалтирь 139:9",
      "text": "Не дай, Господи, желаемого нечестивому; не дай успеха злому замыслу его: они возгордятся."
    },
    {
      "chapter": 139,
      "verse": 10,
      "name": "Псалтирь 139:10",
      "text": "Да покроет головы окружающих меня зло собственных уст их."
    },
    {
      "chapter": 139,
      "verse": 11,
      "name": "Псалтирь 139:11",
      "text": "Да падут на них горящие угли; да будут они повержены в огонь, в пропасти, так, чтобы не встали."
    },
    {
      "chapter": 139,
      "verse": 12,
      "name": "Псалтирь 139:12",
      "text": "Человек злоязычный не утвердится на земле; зло увлечет притеснителя в погибель."
    },
    {
      "chapter": 139,
      "verse": 13,
      "name": "Псалтирь 139:13",
      "text": "Знаю, что Господь сотворит суд угнетенным и справедливость бедным."
    },
    {
      "chapter": 139,
      "verse": 14,
      "name": "Псалтирь 139:14",
      "text": "Так! праведные будут славить имя Твое; непорочные будут обитать пред лицем Твоим. "
    }
  ]
}
